rapyer/__init__.py
rapyer/base.py
rapyer/config.py
rapyer/context.py
rapyer/errors/__init__.py
rapyer/errors/base.py
rapyer/fields/__init__.py
rapyer/fields/expression.py
rapyer/fields/index.py
rapyer/fields/key.py
rapyer/init.py
rapyer/links.py
rapyer/types/__init__.py
rapyer/types/base.py
rapyer/types/byte.py
rapyer/types/convert.py
rapyer/types/datetime.py
rapyer/types/dct.py
rapyer/types/float.py
rapyer/types/init.py
rapyer/types/integer.py
rapyer/types/lst.py
rapyer/types/string.py
rapyer/typing_support.py
rapyer/utils/__init__.py
rapyer/utils/annotation.py
rapyer/utils/fields.py
rapyer/utils/pythonic.py
rapyer/utils/redis.py
rapyer-1.1.4.dist-info/METADATA
rapyer-1.1.4.dist-info/WHEEL
rapyer-1.1.4.dist-info/RECORD
