Metadata-Version: 2.4
Name: rapyer
Version: 1.1.4
Summary: Pydantic models with Redis as the backend
License: MIT
Keywords: redis,redis-json,pydantic,pydantic-v2,orm,database,async,nosql,cache,key-value,data-modeling,python,backend,storage,serialization,validation
Author: YedidyaHKfir
Author-email: yedidyakfir@gmail.com
Requires-Python: >=3.10,<3.14
Classifier: Development Status :: 4 - Beta
Classifier: Intended Audience :: Developers
Classifier: License :: OSI Approved :: MIT License
Classifier: Programming Language :: Python :: 3
Classifier: Programming Language :: Python :: 3.10
Classifier: Programming Language :: Python :: 3.11
Classifier: Programming Language :: Python :: 3.12
Classifier: Programming Language :: Python :: 3.13
Classifier: Framework :: Pydantic
Classifier: Framework :: Pydantic :: 2
Classifier: Framework :: AsyncIO
Classifier: Topic :: Database
Classifier: Topic :: Database :: Database Engines/Servers
Classifier: Topic :: Software Development :: Libraries :: Python Modules
Classifier: Typing :: Typed
Classifier: Operating System :: OS Independent
Requires-Dist: pydantic (>=2.11.0,<2.13.0)
Requires-Dist: redis[async] (>=6.0.0,<7.1.0)
Project-URL: Bug Tracker, https://github.com/imaginary-cherry/rapyer/issues
Project-URL: Changelog, https://github.com/imaginary-cherry/rapyer/releases
Project-URL: Documentation, https://imaginary-cherry.github.io/rapyer/
Project-URL: Homepage, https://imaginary-cherry.github.io/rapyer/
Project-URL: Repository, https://github.com/imaginary-cherry/rapyer
Project-URL: Source Code, https://github.com/imaginary-cherry/rapyer
